{
    "Myanmar News Websites": [
        {
            "Publication Name": "Eleven Myanmar",
            "Website": "https://elevenmyanmar.com"
        },
        {
            "Publication Name": "Frontier Myanmar",
            "Website": "https://frontiermyanmar.net"
        },
        {
            "Publication Name": "Frontier Myanmar",
            "Website": "https://www.frontiermyanmar.net"
        },
        {
            "Publication Name": "Mizzima News",
            "Website": "https://www.mizzima.com"
        },
        {
            "Publication Name": "Mizzima",
            "Website": "https://www.mizzima.com"
        },
        {
            "Publication Name": "Myanmar Now",
            "Website": "https://www.myanmar-now.org"
        },
        {
            "Publication Name": "Myanmar Times",
            "Website": "https://www.mmtimes.com"
        }
    ]
}